stactools/ecmwf_forecast/__init__.py
stactools/ecmwf_forecast/commands.py
stactools/ecmwf_forecast/constants.py
stactools/ecmwf_forecast/plots.py
stactools/ecmwf_forecast/stac.py
stactools_ecmwf_forecast-0.2.0.dist-info/LICENSE
stactools_ecmwf_forecast-0.2.0.dist-info/METADATA
stactools_ecmwf_forecast-0.2.0.dist-info/WHEEL
stactools_ecmwf_forecast-0.2.0.dist-info/top_level.txt
stactools_ecmwf_forecast-0.2.0.dist-info/RECORD
