Metadata-Version: 2.1
Name: stactools-ecmwf-forecast
Version: 0.2.0
Summary: "stactools package to generate STAC items for ECMWF forecast products."
Home-page: https://github.com/stactools-packages/ecmwf-forecast
Author: stac-utils
Author-email: taugspurger@microsoft.com
Project-URL: Documentation, https://stactools-ecmwf-forecast.readthedocs.io/en/latest/
Project-URL: Issues, https://github.com/stactools-packages/ecmwf-forecast/issues
Keywords: stactools,pystac,catalog,STAC,ecmwf
Classifier: Development Status :: 4 - Beta
Classifier: License :: OSI Approved :: Apache Software License
Classifier: Programming Language :: Python :: 3.10
Classifier: Programming Language :: Python :: 3.11
Classifier: Programming Language :: Python :: 3.12
Requires-Python: >3.10
License-File: LICENSE
Requires-Dist: stactools >=0.2.6
Requires-Dist: xarray
Requires-Dist: cfgrib
Requires-Dist: fsspec
